README.md
setup.py
krtool/__init__.py
krtool.egg-info/PKG-INFO
krtool.egg-info/SOURCES.txt
krtool.egg-info/dependency_links.txt
krtool.egg-info/requires.txt
krtool.egg-info/top_level.txt
krtool/mysql/__init__.py
krtool/mysql/mysql.py