Metadata-Version: 2.4
Name: krtool
Version: 1.0.0
Summary: Perform simple operations on the MySQL database without entering SQL commands.
Author: Xuchang Su
Author-email: krlrtear@163.com
Keywords: python,windows,mysql
Classifier: Development Status :: 1 - Planning
Classifier: Intended Audience :: Developers
Classifier: Programming Language :: Python :: 3
Classifier: Operating System :: Microsoft :: Windows
Requires-Dist: pymysql
Dynamic: author
Dynamic: author-email
Dynamic: classifier
Dynamic: description
Dynamic: description-content-type
Dynamic: keywords
Dynamic: requires-dist
Dynamic: summary
